{
	"id": "92ac1259-40f5-4b62-99f4-aea059006ac2",
	"name": "QA",
	"values": [
		{
			"key": "token",
			"value": "4a0bb093cf258b36f24c1383a3d3f68b6379dbd6",
			"enabled": true
		},
		{
			"key": "baseURLTasks",
			"value": "https://api.todoist.com/rest/v1/tasks",
			"enabled": true
		},
		{
			"key": "taskName\n",
			"value": "Buy Milk",
			"enabled": true
		},
		{
			"key": "taskId",
			"value": 4682049940,
			"enabled": true
		}
	],
	"_postman_variable_scope": "environment",
	"_postman_exported_at": "2021-03-23T02:01:55.272Z",
	"_postman_exported_using": "Postman/8.0.7"
}